readme_agent/__init__.py
readme_agent/cli.py
readme_agent/agent/__init__.py
readme_agent/agent/readme_agent.py
readme_agent/scanner/__init__.py
readme_agent/scanner/repo_scanner.py
readme_agent-0.2.1.dist-info/licenses/LICENSE
readme_agent-0.2.1.dist-info/METADATA
readme_agent-0.2.1.dist-info/WHEEL
readme_agent-0.2.1.dist-info/entry_points.txt
readme_agent-0.2.1.dist-info/top_level.txt
readme_agent-0.2.1.dist-info/RECORD
