Metadata-Version: 2.4
Name: readme-agent
Version: 0.2.1
Summary: Agentic CLI tool to auto-generate professional README.md files
Author-email: Tanmay Joshi <joshi.tanm@northeastern.edu>
License-Expression: MIT
License-File: LICENSE
Requires-Dist: typer>=0.9
Requires-Dist: openai
Dynamic: license-file
